{"took":45,"timed_out":false,"_shards":{"total":50,"successful":50,"skipped":0,"failed":0},"hits":{"total":{"value":2494,"relation":"eq"},"max_score":26.918941,"hits":[{"_index":"edgar_file","_id":"0001133228-25-011788:tet-efp18271_ncsrs.htm","_score":26.918941,"_source":{"ciks":["0001944285"],"period_ending":"2025-08-31","file_num":["811-23823"],"display_names":["Tema ETF Trust  (CIK 0001944285)"],"xsl":null,"sequence":1,"root_forms":["N-CSRS"],"file_date":"2025-11-06","biz_states":["DC"],"sics":[],"form":"N-CSRS","adsh":"0001133228-25-011788","film_num":["251457487"],"biz_locations":["Washington, DC"],"file_type":"N-CSRS","file_description":"TEMA ETF TRUST - N-CSRS","inc_states":["DE"],"items":[]}},{"_index":"edgar_file","_id":"0001133228-24-009823:tf-efp10058_ncsrs.htm","_score":26.828516,"_source":{"ciks":["0001944285"],"period_ending":"2024-08-31","file_num":["811-23823"],"display_names":["Tema ETF Trust  (CIK 0001944285)"],"xsl":null,"sequence":1,"root_forms":["N-CSRS"],"file_date":"2024-10-30","biz_states":["DC"],"sics":[],"form":"N-CSRS","adsh":"0001133228-24-009823","film_num":["241407451"],"biz_locations":["Washington, DC"],"file_type":"N-CSRS","file_description":"TEMA FINANCIAL - N-CSRS","inc_states":["DE"],"items":[]}},{"_index":"edgar_file","_id":"0001839882-23-028709:tema-ncsrs_083123.htm","_score":26.784307,"_source":{"ciks":["0001944285"],"period_ending":"2023-08-31","file_num":["811-23823"],"display_names":["Tema ETF Trust  (CIK 0001944285)"],"xsl":null,"sequence":1,"root_forms":["N-CSRS"],"file_date":"2023-10-30","biz_states":["DC"],"sics":[],"form":"N-CSRS","adsh":"0001839882-23-028709","film_num":["231358119"],"biz_locations":["Washington, DC"],"file_type":"N-CSRS","file_description":"CERTIFIED SEMI-ANNUAL SHAREHOLDER REPORT","inc_states":["DE"],"items":[]}},{"_index":"edgar_file","_id":"0001999371-25-021464:tema-497_123126.htm","_score":26.507164,"_source":{"ciks":["0001944285"],"period_ending":null,"file_num":["333-267188"],"display_names":["Tema ETF Trust  (CIK 0001944285)"],"xsl":null,"sequence":1,"root_forms":["497"],"file_date":"2025-12-31","biz_states":["DC"],"sics":[],"form":"497","adsh":"0001999371-25-021464","film_num":["251617583"],"biz_locations":["Washington, DC"],"file_type":"497","file_description":"DEFINITIVE MATERIALS","inc_states":["DE"],"items":[]}},{"_index":"edgar_file","_id":"0001145549-25-029665:primary_doc.xml","_score":26.453999,"_source":{"ciks":["0001944285"],"period_ending":"2025-02-28","file_num":["811-23823"],"display_names":["Tema ETF Trust  (CIK 0001944285)"],"xsl":"xslFormN-CEN_X01","schema_version":"X0404","sequence":1,"root_forms":["N-CEN"],"file_date":"2025-05-13","biz_states":["DC"],"sics":[],"form":"N-CEN/A","adsh":"0001145549-25-029665","film_num":["25941155"],"biz_locations":["Washington, DC"],"file_type":"N-CEN/A","file_description":null,"inc_states":["DE"],"items":[]}},{"_index":"edgar_file","_id":"0000894189-25-003937:primary_doc.xml","_score":26.444286,"_source":{"ciks":["0001944285"],"period_ending":"2025-02-28","file_num":["333-267188"],"display_names":["Tema ETF Trust  (CIK 0001944285)"],"xsl":"xsl24F-2NT","schema_version":"X0102","sequence":1,"root_forms":["24F-2NT"],"file_date":"2025-05-20","biz_states":["DC"],"sics":[],"form":"24F-2NT","adsh":"0000894189-25-003937","film_num":["25969090"],"biz_locations":["Washington, DC"],"file_type":"24F-2NT","file_description":null,"inc_states":["DE"],"items":[]}},{"_index":"edgar_file","_id":"0001133228-25-005492:tetft-efp15123_ncsr.htm","_score":26.34627,"_source":{"ciks":["0001944285"],"period_ending":"2025-02-28","file_num":["811-23823"],"display_names":["Tema ETF Trust  (CIK 0001944285)"],"xsl":null,"sequence":1,"root_forms":["N-CSR"],"file_date":"2025-05-09","biz_states":["DC"],"sics":[],"form":"N-CSR","adsh":"0001133228-25-005492","film_num":["25931050"],"biz_locations":["Washington, DC"],"file_type":"N-CSR","file_description":"TEMA ETF TRUST - N-CSR","inc_states":["DE"],"items":[]}},{"_index":"edgar_file","_id":"0001999371-25-013852:ex99-i.htm","_score":26.329618,"_source":{"ciks":["0001944285"],"period_ending":null,"file_num":["811-23823"],"display_names":["Tema ETF Trust  (CIK 0001944285)"],"xsl":null,"sequence":"3","root_forms":["485BPOS"],"file_date":"2025-09-23","biz_states":["DC"],"sics":[],"form":"485BPOS","adsh":"0001999371-25-013852","film_num":["251334407"],"biz_locations":["Washington, DC"],"file_type":"EX-99.(I)","file_description":"CONSENT OF COUNSEL","inc_states":["DE"],"items":[]}},{"_index":"edgar_file","_id":"0001387131-23-005031:filename1.htm","_score":26.325382,"_source":{"ciks":["0001944285"],"period_ending":null,"file_num":[],"display_names":["Tema ETF Trust  (CIK 0001944285)"],"xsl":null,"sequence":1,"root_forms":["CORRESP"],"file_date":"2023-04-21","biz_states":["DC"],"sics":[],"form":"CORRESP","adsh":"0001387131-23-005031","film_num":[],"biz_locations":["Washington, DC"],"file_type":"CORRESP","file_description":null,"inc_states":["DE"],"items":[]}},{"_index":"edgar_file","_id":"0001438934-25-002008:primary_doc.xml","_score":26.319738,"_source":{"ciks":["0001944285"],"period_ending":"2025-06-30","file_num":["811-23823"],"display_names":["Tema ETF Trust  (CIK 0001944285)"],"xsl":"xslN-PX_X01","sequence":1,"root_forms":["N-PX"],"file_date":"2025-08-27","biz_states":["DC"],"sics":[],"form":"N-PX","adsh":"0001438934-25-002008","film_num":["251262839"],"biz_locations":["Washington, DC"],"file_type":"N-PX","file_description":null,"inc_states":["DE"],"items":[]}},{"_index":"edgar_file","_id":"0001999371-25-008348:ex99-j.htm","_score":26.319603,"_source":{"ciks":["0001944285"],"period_ending":null,"file_num":["811-23823"],"display_names":["Tema ETF Trust  (CIK 0001944285)"],"xsl":null,"sequence":"5","root_forms":["485BPOS"],"file_date":"2025-06-26","biz_states":["DC"],"sics":[],"form":"485BPOS","adsh":"0001999371-25-008348","film_num":["251078574"],"biz_locations":["Washington, DC"],"file_type":"EX-99.(J)","file_description":"CONSENT OF INDEPENDENT REGISTERED PUBLIC ACCOUNTING FIRM","inc_states":["DE"],"items":[]}},{"_index":"edgar_file","_id":"0001999371-25-008558:tema-497j_0630325.htm","_score":26.290257,"_source":{"ciks":["0001944285"],"period_ending":null,"file_num":["333-267188"],"display_names":["Tema ETF Trust  (CIK 0001944285)"],"xsl":null,"sequence":1,"root_forms":["497J"],"file_date":"2025-06-30","biz_states":["DC"],"sics":[],"form":"497J","adsh":"0001999371-25-008558","film_num":["251092785"],"biz_locations":["Washington, DC"],"file_type":"497J","file_description":"CERTIFICATION OF NO CHANGE","inc_states":["DE"],"items":[]}},{"_index":"edgar_file","_id":"0001999371-26-002895:tema-def14c_020926.htm","_score":26.272057,"_source":{"ciks":["0001944285"],"period_ending":"2026-02-09","file_num":["811-23823"],"display_names":["Tema ETF Trust  (CIK 0001944285)"],"xsl":null,"sequence":1,"root_forms":["DEF 14C"],"file_date":"2026-02-09","biz_states":["DC"],"sics":[],"form":"DEF 14C","adsh":"0001999371-26-002895","film_num":["26612609"],"biz_locations":["Washington, DC"],"file_type":"DEF 14C","file_description":"DEFINITIVE INFORMATION STATEMENT","inc_states":["DE"],"items":[]}},{"_index":"edgar_file","_id":"9999999995-23-001252:primary_doc.xml","_score":26.235657,"_source":{"ciks":["0001944285"],"period_ending":null,"file_num":["333-267188"],"display_names":["Tema ETF Trust  (CIK 0001944285)"],"xsl":"xslEFFECTX01","schema_version":"X0101","sequence":1,"root_forms":["EFFECT"],"file_date":"2023-05-03","biz_states":["DC"],"sics":[],"form":"EFFECT","adsh":"9999999995-23-001252","film_num":["23886169"],"biz_locations":["Washington, DC"],"file_type":"EFFECT","file_description":null,"inc_states":["DE"],"items":[]}},{"_index":"edgar_file","_id":"0001999371-25-017546:ex99-a1.htm","_score":26.216988,"_source":{"ciks":["0001944285","0002056807"],"period_ending":null,"file_num":["803-00290","803-00290-01"],"display_names":["Tema ETF Trust  (CIK 0001944285)","TEMA ETFS LLC  (CIK 0002056807)"],"xsl":null,"sequence":3,"root_forms":["40-APP"],"file_date":"2025-11-12","biz_states":["DC","NY"],"sics":[],"form":"40-APP","adsh":"0001999371-25-017546","film_num":["251474395","251474397"],"biz_locations":["Washington, DC","New York, NY"],"file_type":"EX-99.(A)(1)","file_description":"AUTHORIZATION OF TEMA ETF TRUST","inc_states":["DE","DE"],"items":[]}},{"_index":"edgar_file","_id":"0001999371-25-008182:tema-485bxt_062425.htm","_score":26.150545,"_source":{"ciks":["0001944285"],"period_ending":null,"file_num":["811-23823"],"display_names":["Tema ETF Trust  (CIK 0001944285)"],"xsl":null,"sequence":1,"root_forms":["485BXT"],"file_date":"2025-06-24","biz_states":["DC"],"sics":[],"form":"485BXT","adsh":"0001999371-25-008182","film_num":["251068091"],"biz_locations":["Washington, DC"],"file_type":"485BXT","file_description":"POST EFFECTIVE AMENDMENT","inc_states":["DE"],"items":[]}},{"_index":"edgar_file","_id":"0001999371-26-001898:tema_pre14c-012826.htm","_score":26.092241,"_source":{"ciks":["0001944285"],"period_ending":"2026-01-28","file_num":["811-23823"],"display_names":["Tema ETF Trust  (CIK 0001944285)"],"xsl":null,"sequence":1,"root_forms":["PRE 14C"],"file_date":"2026-01-28","biz_states":["DC"],"sics":[],"form":"PRE 14C","adsh":"0001999371-26-001898","film_num":["26573315"],"biz_locations":["Washington, DC"],"file_type":"PRE 14C","file_description":"PRELIMINARY INFORMATION STATEMENT","inc_states":["DE"],"items":[]}},{"_index":"edgar_file","_id":"0001999371-25-003099:ex99-h4.htm","_score":26.085608,"_source":{"ciks":["0001944285"],"period_ending":null,"file_num":["811-23823"],"display_names":["Tema ETF Trust  (CIK 0001944285)"],"xsl":null,"sequence":"5","root_forms":["485BPOS"],"file_date":"2025-03-25","biz_states":["DC"],"sics":[],"form":"485BPOS","adsh":"0001999371-25-003099","film_num":["25767901"],"biz_locations":["Washington, DC"],"file_type":"EX-99.H3","file_description":"INDEX SUB-LICENSE AGREEMENT","inc_states":["DE"],"items":[]}},{"_index":"edgar_file","_id":"0001999371-25-011344:tema-485bxt_081425.htm","_score":26.080917,"_source":{"ciks":["0001944285"],"period_ending":null,"file_num":["811-23823"],"display_names":["Tema ETF Trust  (CIK 0001944285)"],"xsl":null,"sequence":1,"root_forms":["485BXT"],"file_date":"2025-08-14","biz_states":["DC"],"sics":[],"form":"485BXT","adsh":"0001999371-25-011344","film_num":["251217814"],"biz_locations":["Washington, DC"],"file_type":"485BXT","file_description":"POST-EFFECTIVE AMENDMENT","inc_states":["DE"],"items":[]}},{"_index":"edgar_file","_id":"0001999371-24-005270:tema-ncsr_022924.htm","_score":26.064812,"_source":{"ciks":["0001944285"],"period_ending":"2024-02-29","file_num":["811-23823"],"display_names":["Tema ETF Trust  (CIK 0001944285)"],"xsl":null,"sequence":1,"root_forms":["N-CSR"],"file_date":"2024-04-29","biz_states":["DC"],"sics":[],"form":"N-CSR","adsh":"0001999371-24-005270","film_num":["24887537"],"biz_locations":["Washington, DC"],"file_type":"N-CSR","file_description":"CERTIFIED ANNUAL SHAREHOLDER REPORT","inc_states":["DE"],"items":[]}},{"_index":"edgar_file","_id":"0000894189-24-002814:primary_doc.xml","_score":26.048046,"_source":{"ciks":["0001944285"],"period_ending":"2024-02-29","file_num":["333-267188"],"display_names":["Tema ETF Trust  (CIK 0001944285)"],"xsl":"xsl24F-2NT","schema_version":"X0101","sequence":1,"root_forms":["24F-2NT"],"file_date":"2024-04-29","biz_states":["DC"],"sics":[],"form":"24F-2NT","adsh":"0000894189-24-002814","film_num":["24890196"],"biz_locations":["Washington, DC"],"file_type":"24F-2NT","file_description":null,"inc_states":["DE"],"items":[]}},{"_index":"edgar_file","_id":"0001145549-24-024071:temacontrolsletter.htm","_score":26.029453,"_source":{"ciks":["0001944285"],"period_ending":"2024-02-29","file_num":["811-23823"],"display_names":["Tema ETF Trust  (CIK 0001944285)"],"xsl":null,"sequence":2,"root_forms":["N-CEN"],"file_date":"2024-04-24","biz_states":["DC"],"sics":[],"form":"N-CEN","adsh":"0001145549-24-024071","film_num":["24869902"],"biz_locations":["Washington, DC"],"file_type":"INTERNAL CONTROL RPT","file_description":"COHEN INTERNAL CONTROLS LETTER","inc_states":["DE"],"items":[]}},{"_index":"edgar_file","_id":"0001839882-23-010118:ex99-28m.htm","_score":26.02445,"_source":{"ciks":["0001944285"],"period_ending":null,"file_num":["811-23823"],"display_names":["Tema ETF Trust  (CIK 0001944285)"],"xsl":null,"sequence":11,"root_forms":["N-1A"],"file_date":"2023-04-21","biz_states":["DC"],"sics":[],"form":"N-1A/A","adsh":"0001839882-23-010118","film_num":["23836871"],"biz_locations":["Washington, DC"],"file_type":"EX-99.28(M)","file_description":"DISTRIBUTION AND SERVICE PLAN","inc_states":["DE"],"items":[]}},{"_index":"edgar_file","_id":"0001999371-25-012888:ex99-i.htm","_score":25.996105,"_source":{"ciks":["0001944285"],"period_ending":null,"file_num":["811-23823"],"display_names":["Tema ETF Trust  (CIK 0001944285)"],"xsl":null,"sequence":"3","root_forms":["485BPOS"],"file_date":"2025-09-09","biz_states":["DC"],"sics":[],"form":"485BPOS","adsh":"0001999371-25-012888","film_num":["251301217"],"biz_locations":["Washington, DC"],"file_type":"EX-99.(I)","file_description":"CONSENT OF COUNSEL","inc_states":["DE"],"items":[]}},{"_index":"edgar_file","_id":"0001999371-25-012264:longevity-485bxt_082825.htm","_score":25.982271,"_source":{"ciks":["0001944285"],"period_ending":null,"file_num":["811-23823"],"display_names":["Tema ETF Trust  (CIK 0001944285)"],"xsl":null,"sequence":1,"root_forms":["485BXT"],"file_date":"2025-08-28","biz_states":["DC"],"sics":[],"form":"485BXT","adsh":"0001999371-25-012264","film_num":["251273078"],"biz_locations":["Washington, DC"],"file_type":"485BXT","file_description":"POST EFFECTIVE AMENDMENT","inc_states":["DE"],"items":[]}},{"_index":"edgar_file","_id":"0001839882-24-042809:ex99-j.htm","_score":25.958258,"_source":{"ciks":["0001944285"],"period_ending":null,"file_num":["811-23823"],"display_names":["Tema ETF Trust  (CIK 0001944285)"],"xsl":null,"sequence":"4","root_forms":["485BPOS"],"file_date":"2024-12-02","biz_states":["DC"],"sics":[],"form":"485BPOS","adsh":"0001839882-24-042809","film_num":["241520218"],"biz_locations":["Washington, DC"],"file_type":"EX-99.(J)","file_description":"CONSENT OF INDEPENDENT REGISTERED PUBLIC ACCOUNTING FIRM","inc_states":["DE"],"items":[]}},{"_index":"edgar_file","_id":"0001999371-25-017103:longevity-485bxt_110625.htm","_score":25.95694,"_source":{"ciks":["0001944285"],"period_ending":null,"file_num":["811-23823"],"display_names":["Tema ETF Trust  (CIK 0001944285)"],"xsl":null,"sequence":1,"root_forms":["485BXT"],"file_date":"2025-11-06","biz_states":["DC"],"sics":[],"form":"485BXT","adsh":"0001999371-25-017103","film_num":["251457733"],"biz_locations":["Washington, DC"],"file_type":"485BXT","file_description":"POST-EFFECTIVE AMENDMENT","inc_states":["DE"],"items":[]}},{"_index":"edgar_file","_id":"0001145549-24-024071:primary_doc.xml","_score":25.946789,"_source":{"ciks":["0001944285"],"period_ending":"2024-02-29","file_num":["811-23823"],"display_names":["Tema ETF Trust  (CIK 0001944285)"],"xsl":"xslFormN-CEN_X01","schema_version":"X0404","sequence":1,"root_forms":["N-CEN"],"file_date":"2024-04-24","biz_states":["DC"],"sics":[],"form":"N-CEN","adsh":"0001145549-24-024071","film_num":["24869902"],"biz_locations":["Washington, DC"],"file_type":"N-CEN","file_description":null,"inc_states":["DE"],"items":[]}},{"_index":"edgar_file","_id":"0001999371-25-003744:longevity-485bxt_040325.htm","_score":25.933193,"_source":{"ciks":["0001944285"],"period_ending":null,"file_num":["811-23823"],"display_names":["Tema ETF Trust  (CIK 0001944285)"],"xsl":null,"sequence":1,"root_forms":["485BXT"],"file_date":"2025-04-03","biz_states":["DC"],"sics":[],"form":"485BXT","adsh":"0001999371-25-003744","film_num":["25808863"],"biz_locations":["Washington, DC"],"file_type":"485BXT","file_description":"POST EFFECTIVE AMENDMENT","inc_states":["DE"],"items":[]}},{"_index":"edgar_file","_id":"0001999371-25-010376:moats-485bxt_073125.htm","_score":25.927391,"_source":{"ciks":["0001944285"],"period_ending":null,"file_num":["811-23823"],"display_names":["Tema ETF Trust  (CIK 0001944285)"],"xsl":null,"sequence":1,"root_forms":["485BXT"],"file_date":"2025-07-31","biz_states":["DC"],"sics":[],"form":"485BXT","adsh":"0001999371-25-010376","film_num":["251171463"],"biz_locations":["Washington, DC"],"file_type":"485BXT","file_description":"POST EFFECTIVE AMENDMENT","inc_states":["DE"],"items":[]}},{"_index":"edgar_file","_id":"0001387131-23-011459:tema-485bxt_92123.htm","_score":25.915451,"_source":{"ciks":["0001944285"],"period_ending":null,"file_num":["811-23823"],"display_names":["Tema ETF Trust  (CIK 0001944285)"],"xsl":null,"sequence":1,"root_forms":["485BXT"],"file_date":"2023-09-21","biz_states":["DC"],"sics":[],"form":"485BXT","adsh":"0001387131-23-011459","film_num":["231269126"],"biz_locations":["Washington, DC"],"file_type":"485BXT","file_description":"POST-EFFECTIVE AMENDMENT","inc_states":["DE"],"items":[]}},{"_index":"edgar_file","_id":"0001999371-24-008242:tema-497j_070324.htm","_score":25.91455,"_source":{"ciks":["0001944285"],"period_ending":null,"file_num":["333-267188"],"display_names":["Tema ETF Trust  (CIK 0001944285)"],"xsl":null,"sequence":1,"root_forms":["497J"],"file_date":"2024-07-03","biz_states":["DC"],"sics":[],"form":"497J","adsh":"0001999371-24-008242","film_num":["241099682"],"biz_locations":["Washington, DC"],"file_type":"497J","file_description":"CERTIFICATION OF NO CHANGE IN DEFINITIVE MATERIALS","inc_states":["DE"],"items":[]}},{"_index":"edgar_file","_id":"0001999371-25-020653:longevity-485bxt_121825.htm","_score":25.8929,"_source":{"ciks":["0001944285"],"period_ending":null,"file_num":["811-23823"],"display_names":["Tema ETF Trust  (CIK 0001944285)"],"xsl":null,"sequence":1,"root_forms":["485BXT"],"file_date":"2025-12-18","biz_states":["DC"],"sics":[],"form":"485BXT","adsh":"0001999371-25-020653","film_num":["251582898"],"biz_locations":["Washington, DC"],"file_type":"485BXT","file_description":"POST-EFFECTIVE AMENDMENT","inc_states":["DE"],"items":[]}},{"_index":"edgar_file","_id":"0001999371-25-001263:longevity-485bxt_020625.htm","_score":25.870306,"_source":{"ciks":["0001944285"],"period_ending":null,"file_num":["811-23823"],"display_names":["Tema ETF Trust  (CIK 0001944285)"],"xsl":null,"sequence":1,"root_forms":["485BXT"],"file_date":"2025-02-06","biz_states":["DC"],"sics":[],"form":"485BXT","adsh":"0001999371-25-001263","film_num":["25598099"],"biz_locations":["Washington, DC"],"file_type":"485BXT","file_description":"POST-EFFECTIVE AMENDMENT","inc_states":["DE"],"items":[]}},{"_index":"edgar_file","_id":"0001145549-25-029627:primary_doc.xml","_score":25.869696,"_source":{"ciks":["0001944285"],"period_ending":"2025-02-28","file_num":["811-23823"],"display_names":["Tema ETF Trust  (CIK 0001944285)"],"xsl":"xslFormN-CEN_X01","schema_version":"X0404","sequence":1,"root_forms":["N-CEN"],"file_date":"2025-05-13","biz_states":["DC"],"sics":[],"form":"N-CEN","adsh":"0001145549-25-029627","film_num":["25939197"],"biz_locations":["Washington, DC"],"file_type":"N-CEN","file_description":null,"inc_states":["DE"],"items":[]}},{"_index":"edgar_file","_id":"0001999371-24-007970:ex99-j.htm","_score":25.852646,"_source":{"ciks":["0001944285"],"period_ending":null,"file_num":["811-23823"],"display_names":["Tema ETF Trust  (CIK 0001944285)"],"xsl":null,"sequence":4,"root_forms":["485BPOS"],"file_date":"2024-06-28","biz_states":["DC"],"sics":[],"form":"485BPOS","adsh":"0001999371-24-007970","film_num":["241085009"],"biz_locations":["Washington, DC"],"file_type":"EX-99.(J)","file_description":"CONSENT OF INDEPENDENT REGISTERED PUBLIC ACCOUNTING FIRM","inc_states":["DE"],"items":[]}},{"_index":"edgar_file","_id":"0001438934-24-001936:primary_doc.xml","_score":25.851585,"_source":{"ciks":["0001944285"],"period_ending":"2024-06-30","file_num":["811-23823"],"display_names":["Tema ETF Trust  (CIK 0001944285)"],"xsl":"xslN-PX_X01","sequence":1,"root_forms":["N-PX"],"file_date":"2024-09-03","biz_states":["DC"],"sics":[],"form":"N-PX","adsh":"0001438934-24-001936","film_num":["241273729"],"biz_locations":["Washington, DC"],"file_type":"N-PX","file_description":null,"inc_states":["DE"],"items":[]}},{"_index":"edgar_file","_id":"0001999371-25-010370:longevity-485bxt_073125.htm","_score":25.834345,"_source":{"ciks":["0001944285"],"period_ending":null,"file_num":["811-23823"],"display_names":["Tema ETF Trust  (CIK 0001944285)"],"xsl":null,"sequence":1,"root_forms":["485BXT"],"file_date":"2025-07-31","biz_states":["DC"],"sics":[],"form":"485BXT","adsh":"0001999371-25-010370","film_num":["251171402"],"biz_locations":["Washington, DC"],"file_type":"485BXT","file_description":"POST EFFECTIVE AMENDMENT","inc_states":["DE"],"items":[]}},{"_index":"edgar_file","_id":"0001387131-23-009979:tema-485bxt_081823.htm","_score":25.796883,"_source":{"ciks":["0001944285"],"period_ending":null,"file_num":["811-23823"],"display_names":["Tema ETF Trust  (CIK 0001944285)"],"xsl":null,"sequence":1,"root_forms":["485BXT"],"file_date":"2023-08-18","biz_states":["DC"],"sics":[],"form":"485BXT","adsh":"0001387131-23-009979","film_num":["231186148"],"biz_locations":["Washington, DC"],"file_type":"485BXT","file_description":"POST-EFFECTIVE AMENDMENT","inc_states":["DE"],"items":[]}},{"_index":"edgar_file","_id":"0001999371-25-019356:tema-485bxt_120325.htm","_score":25.78625,"_source":{"ciks":["0001944285"],"period_ending":null,"file_num":["811-23823"],"display_names":["Tema ETF Trust  (CIK 0001944285)"],"xsl":null,"sequence":1,"root_forms":["485BXT"],"file_date":"2025-12-03","biz_states":["DC"],"sics":[],"form":"485BXT","adsh":"0001999371-25-019356","film_num":["251546515"],"biz_locations":["Washington, DC"],"file_type":"485BXT","file_description":"POST-EFFECTIVE AMENDMENT","inc_states":["DE"],"items":[]}},{"_index":"edgar_file","_id":"0001999371-25-008885:tema-485bxt_070925.htm","_score":25.770716,"_source":{"ciks":["0001944285"],"period_ending":null,"file_num":["811-23823"],"display_names":["Tema ETF Trust  (CIK 0001944285)"],"xsl":null,"sequence":1,"root_forms":["485BXT"],"file_date":"2025-07-09","biz_states":["DC"],"sics":[],"form":"485BXT","adsh":"0001999371-25-008885","film_num":["251114072"],"biz_locations":["Washington, DC"],"file_type":"485BXT","file_description":"POST EFFECTIVE AMENDMENT","inc_states":["DE"],"items":[]}},{"_index":"edgar_file","_id":"0001999371-25-019353:tema-485bxt_120325.htm","_score":25.767788,"_source":{"ciks":["0001944285"],"period_ending":null,"file_num":["811-23823"],"display_names":["Tema ETF Trust  (CIK 0001944285)"],"xsl":null,"sequence":1,"root_forms":["485BXT"],"file_date":"2025-12-03","biz_states":["DC"],"sics":[],"form":"485BXT","adsh":"0001999371-25-019353","film_num":["251546440"],"biz_locations":["Washington, DC"],"file_type":"485BXT","file_description":"POST-EFFECTIVE AMENDMENT","inc_states":["DE"],"items":[]}},{"_index":"edgar_file","_id":"0001999371-25-012267:moats-485bxt_082825.htm","_score":25.756796,"_source":{"ciks":["0001944285"],"period_ending":null,"file_num":["811-23823"],"display_names":["Tema ETF Trust  (CIK 0001944285)"],"xsl":null,"sequence":1,"root_forms":["485BXT"],"file_date":"2025-08-28","biz_states":["DC"],"sics":[],"form":"485BXT","adsh":"0001999371-25-012267","film_num":["251273234"],"biz_locations":["Washington, DC"],"file_type":"485BXT","file_description":"POST EFFECTIVE AMENDMENT","inc_states":["DE"],"items":[]}},{"_index":"edgar_file","_id":"0001999371-26-000967:longevity-485bxt_011526.htm","_score":25.72219,"_source":{"ciks":["0001944285"],"period_ending":null,"file_num":["811-23823"],"display_names":["Tema ETF Trust  (CIK 0001944285)"],"xsl":null,"sequence":1,"root_forms":["485BXT"],"file_date":"2026-01-15","biz_states":["DC"],"sics":[],"form":"485BXT","adsh":"0001999371-26-000967","film_num":["26535632"],"biz_locations":["Washington, DC"],"file_type":"485BXT","file_description":"POST-EFFECTIVE AMENDMENT","inc_states":["DE"],"items":[]}},{"_index":"edgar_file","_id":"0001999371-25-006179:longevity-485bxt_051525.htm","_score":25.718801,"_source":{"ciks":["0001944285"],"period_ending":null,"file_num":["811-23823"],"display_names":["Tema ETF Trust  (CIK 0001944285)"],"xsl":null,"sequence":1,"root_forms":["485BXT"],"file_date":"2025-05-15","biz_states":["DC"],"sics":[],"form":"485BXT","adsh":"0001999371-25-006179","film_num":["25951650"],"biz_locations":["Washington, DC"],"file_type":"485BXT","file_description":"POST EFFECTIVE AMENDMENT","inc_states":["DE"],"items":[]}},{"_index":"edgar_file","_id":"0001839882-25-014165:tema-485bxt_030625.htm","_score":25.711916,"_source":{"ciks":["0001944285"],"period_ending":null,"file_num":["811-23823"],"display_names":["Tema ETF Trust  (CIK 0001944285)"],"xsl":null,"sequence":1,"root_forms":["485BXT"],"file_date":"2025-03-06","biz_states":["DC"],"sics":[],"form":"485BXT","adsh":"0001839882-25-014165","film_num":["25714578"],"biz_locations":["Washington, DC"],"file_type":"485BXT","file_description":"POST EFFECTIVE AMENDMENT","inc_states":["DE"],"items":[]}},{"_index":"edgar_file","_id":"0001387131-23-012426:ex99-i.htm","_score":25.701736,"_source":{"ciks":["0001944285"],"period_ending":null,"file_num":["811-23823"],"display_names":["Tema ETF Trust  (CIK 0001944285)"],"xsl":null,"sequence":5,"root_forms":["485BPOS"],"file_date":"2023-10-20","biz_states":["DC"],"sics":[],"form":"485BPOS","adsh":"0001387131-23-012426","film_num":["231335771"],"biz_locations":["Washington, DC"],"file_type":"EX-99.(I)","file_description":"CONSENT OF COUNSEL","inc_states":["DE"],"items":[]}},{"_index":"edgar_file","_id":"0001145549-25-029665:internalcontrolletter.htm","_score":25.700033,"_source":{"ciks":["0001944285"],"period_ending":"2025-02-28","file_num":["811-23823"],"display_names":["Tema ETF Trust  (CIK 0001944285)"],"xsl":null,"sequence":"2","root_forms":["N-CEN"],"file_date":"2025-05-13","biz_states":["DC"],"sics":[],"form":"N-CEN/A","adsh":"0001145549-25-029665","film_num":["25941155"],"biz_locations":["Washington, DC"],"file_type":"INTERNAL CONTROL RPT","file_description":"TEMA ETF TRUST 2.28.25 INTERNAL CONTROL LETTER","inc_states":["DE"],"items":[]}},{"_index":"edgar_file","_id":"0001387131-23-011939:tema-485bxt_10523.htm","_score":25.698864,"_source":{"ciks":["0001944285"],"period_ending":null,"file_num":["811-23823"],"display_names":["Tema ETF Trust  (CIK 0001944285)"],"xsl":null,"sequence":1,"root_forms":["485BXT"],"file_date":"2023-10-05","biz_states":["DC"],"sics":[],"form":"485BXT","adsh":"0001387131-23-011939","film_num":["231311089"],"biz_locations":["Washington, DC"],"file_type":"485BXT","file_description":"POST-EFFECTIVE AMENDMENT","inc_states":["DE"],"items":[]}},{"_index":"edgar_file","_id":"0001839882-23-010118:ex99-q.htm","_score":25.696589,"_source":{"ciks":["0001944285"],"period_ending":null,"file_num":["811-23823"],"display_names":["Tema ETF Trust  (CIK 0001944285)"],"xsl":null,"sequence":16,"root_forms":["N-1A"],"file_date":"2023-04-21","biz_states":["DC"],"sics":[],"form":"N-1A/A","adsh":"0001839882-23-010118","film_num":["23836871"],"biz_locations":["Washington, DC"],"file_type":"EX-99.(Q)","file_description":"POWER OF ATTORNEY","inc_states":["DE"],"items":[]}},{"_index":"edgar_file","_id":"0001999371-25-003099:ex99-i.htm","_score":25.689463,"_source":{"ciks":["0001944285"],"period_ending":null,"file_num":["811-23823"],"display_names":["Tema ETF Trust  (CIK 0001944285)"],"xsl":null,"sequence":"6","root_forms":["485BPOS"],"file_date":"2025-03-25","biz_states":["DC"],"sics":[],"form":"485BPOS","adsh":"0001999371-25-003099","film_num":["25767901"],"biz_locations":["Washington, DC"],"file_type":"EX-99.I","file_description":"CONSENT OF COUNSEL","inc_states":["DE"],"items":[]}},{"_index":"edgar_file","_id":"0001999371-25-003099:ex99-h3.htm","_score":25.688688,"_source":{"ciks":["0001944285"],"period_ending":null,"file_num":["811-23823"],"display_names":["Tema ETF Trust  (CIK 0001944285)"],"xsl":null,"sequence":"4","root_forms":["485BPOS"],"file_date":"2025-03-25","biz_states":["DC"],"sics":[],"form":"485BPOS","adsh":"0001999371-25-003099","film_num":["25767901"],"biz_locations":["Washington, DC"],"file_type":"EX-99.H3","file_description":"EXPENSE LIMITATION AGREEMENT","inc_states":["DE"],"items":[]}},{"_index":"edgar_file","_id":"0001839882-23-010118:ex99-i.htm","_score":25.681072,"_source":{"ciks":["0001944285"],"period_ending":null,"file_num":["811-23823"],"display_names":["Tema ETF Trust  (CIK 0001944285)"],"xsl":null,"sequence":9,"root_forms":["N-1A"],"file_date":"2023-04-21","biz_states":["DC"],"sics":[],"form":"N-1A/A","adsh":"0001839882-23-010118","film_num":["23836871"],"biz_locations":["Washington, DC"],"file_type":"EX-99.(I)","file_description":"OPINION AND CONSENT OF COUNSEL","inc_states":["DE"],"items":[]}},{"_index":"edgar_file","_id":"0001999371-25-012599:moats-485bxt_090425.htm","_score":25.671124,"_source":{"ciks":["0001944285"],"period_ending":null,"file_num":["811-23823"],"display_names":["Tema ETF Trust  (CIK 0001944285)"],"xsl":null,"sequence":1,"root_forms":["485BXT"],"file_date":"2025-09-04","biz_states":["DC"],"sics":[],"form":"485BXT","adsh":"0001999371-25-012599","film_num":["251294097"],"biz_locations":["Washington, DC"],"file_type":"485BXT","file_description":"POST EFFECTIVE AMENDMENT","inc_states":["DE"],"items":[]}},{"_index":"edgar_file","_id":"0001145549-23-043775:rshov1confidential.htm","_score":25.669538,"_source":{"ciks":["0001944285"],"period_ending":"2023-05-31","file_num":["811-23823"],"display_names":["Tema ETF Trust  (CIK 0001944285)"],"xsl":null,"sequence":2,"root_forms":["NPORT-P"],"file_date":"2023-07-25","biz_states":["DC"],"sics":[],"form":"NPORT-P","adsh":"0001145549-23-043775","film_num":["231108059"],"biz_locations":["Washington, DC"],"file_type":"NPORT-EX","file_description":"PART F","inc_states":["DE"],"items":[]}},{"_index":"edgar_file","_id":"0001839882-23-024174:tema-485bxt_091423.htm","_score":25.663414,"_source":{"ciks":["0001944285"],"period_ending":null,"file_num":["811-23823"],"display_names":["Tema ETF Trust  (CIK 0001944285)"],"xsl":null,"sequence":1,"root_forms":["485BXT"],"file_date":"2023-09-14","biz_states":["DC"],"sics":[],"form":"485BXT","adsh":"0001839882-23-024174","film_num":["231255063"],"biz_locations":["Washington, DC"],"file_type":"485BXT","file_description":"POST-EFFECTIVE AMENDMENT","inc_states":["DE"],"items":[]}},{"_index":"edgar_file","_id":"0001387131-23-012527:tema-497j_102323.htm","_score":25.661236,"_source":{"ciks":["0001944285"],"period_ending":null,"file_num":["333-267188"],"display_names":["Tema ETF Trust  (CIK 0001944285)"],"xsl":null,"sequence":1,"root_forms":["497J"],"file_date":"2023-10-23","biz_states":["DC"],"sics":[],"form":"497J","adsh":"0001387131-23-012527","film_num":["231339708"],"biz_locations":["Washington, DC"],"file_type":"497J","file_description":"NO CHANGE IN DEFINITIVE MATERIALS","inc_states":["DE"],"items":[]}},{"_index":"edgar_file","_id":"0001387131-23-010242:tema_485bxt-082423.htm","_score":25.638073,"_source":{"ciks":["0001944285"],"period_ending":null,"file_num":["811-23823"],"display_names":["Tema ETF Trust  (CIK 0001944285)"],"xsl":null,"sequence":1,"root_forms":["485BXT"],"file_date":"2023-08-24","biz_states":["DC"],"sics":[],"form":"485BXT","adsh":"0001387131-23-010242","film_num":["231202081"],"biz_locations":["Washington, DC"],"file_type":"485BXT","file_description":"POST-EFFECTIVE AMENDMENT","inc_states":["DE"],"items":[]}},{"_index":"edgar_file","_id":"0001999371-25-004378:longevity-485bxt_041725.htm","_score":25.63649,"_source":{"ciks":["0001944285"],"period_ending":null,"file_num":["811-23823"],"display_names":["Tema ETF Trust  (CIK 0001944285)"],"xsl":null,"sequence":1,"root_forms":["485BXT"],"file_date":"2025-04-17","biz_states":["DC"],"sics":[],"form":"485BXT","adsh":"0001999371-25-004378","film_num":["25846720"],"biz_locations":["Washington, DC"],"file_type":"485BXT","file_description":"POST EFFECTIVE AMENDMENT","inc_states":["DE"],"items":[]}},{"_index":"edgar_file","_id":"0001999371-25-008880:longevity-485bxt_070925.htm","_score":25.614716,"_source":{"ciks":["0001944285"],"period_ending":null,"file_num":["811-23823"],"display_names":["Tema ETF Trust  (CIK 0001944285)"],"xsl":null,"sequence":1,"root_forms":["485BXT"],"file_date":"2025-07-09","biz_states":["DC"],"sics":[],"form":"485BXT","adsh":"0001999371-25-008880","film_num":["251113888"],"biz_locations":["Washington, DC"],"file_type":"485BXT","file_description":"POST EFFECTIVE AMENDMENT","inc_states":["DE"],"items":[]}},{"_index":"edgar_file","_id":"0001999371-25-012867:moats-485bxt_090825.htm","_score":25.610212,"_source":{"ciks":["0001944285"],"period_ending":null,"file_num":["811-23823"],"display_names":["Tema ETF Trust  (CIK 0001944285)"],"xsl":null,"sequence":1,"root_forms":["485BXT"],"file_date":"2025-09-08","biz_states":["DC"],"sics":[],"form":"485BXT","adsh":"0001999371-25-012867","film_num":["251300754"],"biz_locations":["Washington, DC"],"file_type":"485BXT","file_description":"POST EFFECTIVE AMENDMENT","inc_states":["DE"],"items":[]}},{"_index":"edgar_file","_id":"0001387131-23-010684:tema_485bxt-083123.htm","_score":25.572613,"_source":{"ciks":["0001944285"],"period_ending":null,"file_num":["811-23823"],"display_names":["Tema ETF Trust  (CIK 0001944285)"],"xsl":null,"sequence":1,"root_forms":["485BXT"],"file_date":"2023-08-31","biz_states":["DC"],"sics":[],"form":"485BXT","adsh":"0001387131-23-010684","film_num":["231228260"],"biz_locations":["Washington, DC"],"file_type":"485BXT","file_description":"DESIGNATION OF A NEW EFFECTIVE DATE","inc_states":["DE"],"items":[]}},{"_index":"edgar_file","_id":"0001999371-25-015111:longevity-485bxt_100925.htm","_score":25.57241,"_source":{"ciks":["0001944285"],"period_ending":null,"file_num":["811-23823"],"display_names":["Tema ETF Trust  (CIK 0001944285)"],"xsl":null,"sequence":1,"root_forms":["485BXT"],"file_date":"2025-10-09","biz_states":["DC"],"sics":[],"form":"485BXT","adsh":"0001999371-25-015111","film_num":["251385715"],"biz_locations":["Washington, DC"],"file_type":"485BXT","file_description":"POST-EFFECTIVE AMENDMENT TO RULE 485(B)","inc_states":["DE"],"items":[]}},{"_index":"edgar_file","_id":"0001387131-23-010881:tema_485bxt-090723.htm","_score":25.560978,"_source":{"ciks":["0001944285"],"period_ending":null,"file_num":["811-23823"],"display_names":["Tema ETF Trust  (CIK 0001944285)"],"xsl":null,"sequence":1,"root_forms":["485BXT"],"file_date":"2023-09-07","biz_states":["DC"],"sics":[],"form":"485BXT","adsh":"0001387131-23-010881","film_num":["231241709"],"biz_locations":["Washington, DC"],"file_type":"485BXT","file_description":"POST-EFFECTIVE AMENDMENT","inc_states":["DE"],"items":[]}},{"_index":"edgar_file","_id":"0001999371-25-008881:family-485bxt_070925.htm","_score":25.527533,"_source":{"ciks":["0001944285"],"period_ending":null,"file_num":["811-23823"],"display_names":["Tema ETF Trust  (CIK 0001944285)"],"xsl":null,"sequence":1,"root_forms":["485BXT"],"file_date":"2025-07-09","biz_states":["DC"],"sics":[],"form":"485BXT","adsh":"0001999371-25-008881","film_num":["251113953"],"biz_locations":["Washington, DC"],"file_type":"485BXT","file_description":"POST EFFECTIVE AMENDMENT","inc_states":["DE"],"items":[]}},{"_index":"edgar_file","_id":"0001999371-25-013852:ex99-j.htm","_score":25.504805,"_source":{"ciks":["0001944285"],"period_ending":null,"file_num":["811-23823"],"display_names":["Tema ETF Trust  (CIK 0001944285)"],"xsl":null,"sequence":"4","root_forms":["485BPOS"],"file_date":"2025-09-23","biz_states":["DC"],"sics":[],"form":"485BPOS","adsh":"0001999371-25-013852","film_num":["251334407"],"biz_locations":["Washington, DC"],"file_type":"EX-99.(J)","file_description":"CONSENT OF INDEPENDENT REGISTERED PUBLIC ACCOUNTING FIRM","inc_states":["DE"],"items":[]}},{"_index":"edgar_file","_id":"0001999371-25-013287:tema-485bxt_091525.htm","_score":25.483967,"_source":{"ciks":["0001944285"],"period_ending":null,"file_num":["811-23823"],"display_names":["Tema ETF Trust  (CIK 0001944285)"],"xsl":null,"sequence":1,"root_forms":["485BXT"],"file_date":"2025-09-16","biz_states":["DC"],"sics":[],"form":"485BXT","adsh":"0001999371-25-013287","film_num":["251315263"],"biz_locations":["Washington, DC"],"file_type":"485BXT","file_description":"POST-EFFECTIVE AMENDMENT","inc_states":["DE"],"items":[]}},{"_index":"edgar_file","_id":"0001999371-26-003143:longevity-485bxt_021226.htm","_score":25.483967,"_source":{"ciks":["0001944285"],"period_ending":null,"file_num":["811-23823"],"display_names":["Tema ETF Trust  (CIK 0001944285)"],"xsl":null,"sequence":1,"root_forms":["485BXT"],"file_date":"2026-02-12","biz_states":["DC"],"sics":[],"form":"485BXT","adsh":"0001999371-26-003143","film_num":["26625419"],"biz_locations":["Washington, DC"],"file_type":"485BXT","file_description":"POST-EFFECTIVE AMENDMENT","inc_states":["DE"],"items":[]}},{"_index":"edgar_file","_id":"0001145549-23-043776:luxv1confidential.htm","_score":25.47061,"_source":{"ciks":["0001944285"],"period_ending":"2023-05-31","file_num":["811-23823"],"display_names":["Tema ETF Trust  (CIK 0001944285)"],"xsl":null,"sequence":2,"root_forms":["NPORT-P"],"file_date":"2023-07-25","biz_states":["DC"],"sics":[],"form":"NPORT-P","adsh":"0001145549-23-043776","film_num":["231108058"],"biz_locations":["Washington, DC"],"file_type":"NPORT-EX","file_description":"PART F","inc_states":["DE"],"items":[]}},{"_index":"edgar_file","_id":"0001999371-25-014005:longevity-485bxt_092525.htm","_score":25.468824,"_source":{"ciks":["0001944285"],"period_ending":null,"file_num":["811-23823"],"display_names":["Tema ETF Trust  (CIK 0001944285)"],"xsl":null,"sequence":1,"root_forms":["485BXT"],"file_date":"2025-09-25","biz_states":["DC"],"sics":[],"form":"485BXT","adsh":"0001999371-25-014005","film_num":["251344009"],"biz_locations":["Washington, DC"],"file_type":"485BXT","file_description":"POST EFFECTIVE AMENDMENT","inc_states":["DE"],"items":[]}},{"_index":"edgar_file","_id":"0001387131-23-012181:tema-485bxt_101223.htm","_score":25.453613,"_source":{"ciks":["0001944285"],"period_ending":null,"file_num":["811-23823"],"display_names":["Tema ETF Trust  (CIK 0001944285)"],"xsl":null,"sequence":1,"root_forms":["485BXT"],"file_date":"2023-10-12","biz_states":["DC"],"sics":[],"form":"485BXT","adsh":"0001387131-23-012181","film_num":["231322443"],"biz_locations":["Washington, DC"],"file_type":"485BXT","file_description":"POST-EFFECTIVE AMENDMENT","inc_states":["DE"],"items":[]}},{"_index":"edgar_file","_id":"0001839882-25-011687:family-485bxt_022725.htm","_score":25.448023,"_source":{"ciks":["0001944285"],"period_ending":null,"file_num":["811-23823"],"display_names":["Tema ETF Trust  (CIK 0001944285)"],"xsl":null,"sequence":1,"root_forms":["485BXT"],"file_date":"2025-02-27","biz_states":["DC"],"sics":[],"form":"485BXT","adsh":"0001839882-25-011687","film_num":["25677186"],"biz_locations":["Washington, DC"],"file_type":"485BXT","file_description":"POST-EFFECTIVE AMENDMENT","inc_states":["DE"],"items":[]}},{"_index":"edgar_file","_id":"0001999371-25-010374:endowment-485bxt_073125.htm","_score":25.422602,"_source":{"ciks":["0001944285"],"period_ending":null,"file_num":["811-23823"],"display_names":["Tema ETF Trust  (CIK 0001944285)"],"xsl":null,"sequence":1,"root_forms":["485BXT"],"file_date":"2025-07-31","biz_states":["DC"],"sics":[],"form":"485BXT","adsh":"0001999371-25-010374","film_num":["251171448"],"biz_locations":["Washington, DC"],"file_type":"485BXT","file_description":"POST EFFECTIVE AMENDMENT","inc_states":["DE"],"items":[]}},{"_index":"edgar_file","_id":"0001839882-24-036440:tema-485bxt_103124.htm","_score":25.414549,"_source":{"ciks":["0001944285"],"period_ending":null,"file_num":["811-23823"],"display_names":["Tema ETF Trust  (CIK 0001944285)"],"xsl":null,"sequence":1,"root_forms":["485BXT"],"file_date":"2024-10-31","biz_states":["DC"],"sics":[],"form":"485BXT","adsh":"0001839882-24-036440","film_num":["241414500"],"biz_locations":["Washington, DC"],"file_type":"485BXT","file_description":"POST EFFECTIVE AMENDMENT","inc_states":["DE"],"items":[]}},{"_index":"edgar_file","_id":"0001999371-25-013938:tema-497j_092425.htm","_score":25.410948,"_source":{"ciks":["0001944285"],"period_ending":null,"file_num":["333-267188"],"display_names":["Tema ETF Trust  (CIK 0001944285)"],"xsl":null,"sequence":1,"root_forms":["497J"],"file_date":"2025-09-24","biz_states":["DC"],"sics":[],"form":"497J","adsh":"0001999371-25-013938","film_num":["251337888"],"biz_locations":["Washington, DC"],"file_type":"497J","file_description":"NO CHANGE IN DEFINITIVE MATERIALS","inc_states":["DE"],"items":[]}},{"_index":"edgar_file","_id":"0001999371-25-012265:familyoffice-485bxt_082825.htm","_score":25.385813,"_source":{"ciks":["0001944285"],"period_ending":null,"file_num":["811-23823"],"display_names":["Tema ETF Trust  (CIK 0001944285)"],"xsl":null,"sequence":1,"root_forms":["485BXT"],"file_date":"2025-08-28","biz_states":["DC"],"sics":[],"form":"485BXT","adsh":"0001999371-25-012265","film_num":["251273113"],"biz_locations":["Washington, DC"],"file_type":"485BXT","file_description":"POST EFFECTIVE AMENDMENT","inc_states":["DE"],"items":[]}},{"_index":"edgar_file","_id":"0001999371-24-015138:tema-8a12b_120324.htm","_score":25.37148,"_source":{"ciks":["0001944285"],"period_ending":null,"file_num":["001-41700"],"display_names":["Tema ETF Trust  (CIK 0001944285)"],"xsl":null,"sequence":1,"root_forms":["8-A12B"],"file_date":"2024-12-03","biz_states":["DC"],"sics":[],"form":"8-A12B","adsh":"0001999371-24-015138","film_num":["241522464"],"biz_locations":["Washington, DC"],"file_type":"8-A12B","file_description":"FORM FOR THE REGISTATION/LISTING OF A CLASS OF SECURITIES","inc_states":["DE"],"items":[]}},{"_index":"edgar_file","_id":"0001145549-24-002275:hrtsvconfidential.htm","_score":25.340305,"_source":{"ciks":["0001944285"],"period_ending":"2023-11-30","file_num":["811-23823"],"display_names":["Tema ETF Trust  (CIK 0001944285)"],"xsl":null,"sequence":2,"root_forms":["NPORT-P"],"file_date":"2024-01-23","biz_states":["DC"],"sics":[],"form":"NPORT-P","adsh":"0001145549-24-002275","film_num":["24551243"],"biz_locations":["Washington, DC"],"file_type":"NPORT-EX","file_description":"PART F","inc_states":["DE"],"items":[]}},{"_index":"edgar_file","_id":"0001999371-24-000614:tema-8a12b_012224.htm","_score":25.329157,"_source":{"ciks":["0001944285"],"period_ending":null,"file_num":["001-41700"],"display_names":["Tema ETF Trust  (CIK 0001944285)"],"xsl":null,"sequence":1,"root_forms":["8-A12B"],"file_date":"2024-01-22","biz_states":["DC"],"sics":[],"form":"8-A12B","adsh":"0001999371-24-000614","film_num":["24547831"],"biz_locations":["Washington, DC"],"file_type":"8-A12B","file_description":"REGISTRATION / LISTING OF A CLASS OF SECURITIES","inc_states":["DE"],"items":[]}},{"_index":"edgar_file","_id":"0001145549-24-002278:cancvconfidential.htm","_score":25.326206,"_source":{"ciks":["0001944285"],"period_ending":"2023-11-30","file_num":["811-23823"],"display_names":["Tema ETF Trust  (CIK 0001944285)"],"xsl":null,"sequence":2,"root_forms":["NPORT-P"],"file_date":"2024-01-23","biz_states":["DC"],"sics":[],"form":"NPORT-P","adsh":"0001145549-24-002278","film_num":["24551246"],"biz_locations":["Washington, DC"],"file_type":"NPORT-EX","file_description":"PART F","inc_states":["DE"],"items":[]}},{"_index":"edgar_file","_id":"0001999371-25-013469:tema-8a12b_091725.htm","_score":25.317564,"_source":{"ciks":["0001944285"],"period_ending":null,"file_num":["001-41700"],"display_names":["Tema ETF Trust  (CIK 0001944285)"],"xsl":null,"sequence":1,"root_forms":["8-A12B"],"file_date":"2025-09-17","biz_states":["DC"],"sics":[],"form":"8-A12B","adsh":"0001999371-25-013469","film_num":["251320139"],"biz_locations":["Washington, DC"],"file_type":"8-A12B","file_description":"FORM OF THE REGISTRATION","inc_states":["DE"],"items":[]}},{"_index":"edgar_file","_id":"0001999371-25-007618:longevity-485bxt_061125.htm","_score":25.305603,"_source":{"ciks":["0001944285"],"period_ending":null,"file_num":["811-23823"],"display_names":["Tema ETF Trust  (CIK 0001944285)"],"xsl":null,"sequence":1,"root_forms":["485BXT"],"file_date":"2025-06-11","biz_states":["DC"],"sics":[],"form":"485BXT","adsh":"0001999371-25-007618","film_num":["251040139"],"biz_locations":["Washington, DC"],"file_type":"485BXT","file_description":"POST-EFFECTIVE AMENDMENT","inc_states":["DE"],"items":[]}},{"_index":"edgar_file","_id":"0001387131-23-012426:ex99-j.htm","_score":25.302814,"_source":{"ciks":["0001944285"],"period_ending":null,"file_num":["811-23823"],"display_names":["Tema ETF Trust  (CIK 0001944285)"],"xsl":null,"sequence":6,"root_forms":["485BPOS"],"file_date":"2023-10-20","biz_states":["DC"],"sics":[],"form":"485BPOS","adsh":"0001387131-23-012426","film_num":["231335771"],"biz_locations":["Washington, DC"],"file_type":"EX-99.(J)","file_description":"CONSENT OF INDEPENDENT REGISTERED PUBLIC ACCOUNTING FIRM","inc_states":["DE"],"items":[]}},{"_index":"edgar_file","_id":"0001387131-23-006648:lux-497_051723.htm","_score":25.294647,"_source":{"ciks":["0001944285"],"period_ending":null,"file_num":["333-267188"],"display_names":["Tema ETF Trust  (CIK 0001944285)"],"xsl":null,"sequence":1,"root_forms":["497"],"file_date":"2023-05-17","biz_states":["DC"],"sics":[],"form":"497","adsh":"0001387131-23-006648","film_num":["23931617"],"biz_locations":["Washington, DC"],"file_type":"497","file_description":"DEFINITIVE MATERIALS","inc_states":["DE"],"items":[]}},{"_index":"edgar_file","_id":"0001999371-25-010366:saudia-485bxt_073125.htm","_score":25.294567,"_source":{"ciks":["0001944285"],"period_ending":null,"file_num":["811-23823"],"display_names":["Tema ETF Trust  (CIK 0001944285)"],"xsl":null,"sequence":1,"root_forms":["485BXT"],"file_date":"2025-07-31","biz_states":["DC"],"sics":[],"form":"485BXT","adsh":"0001999371-25-010366","film_num":["251171356"],"biz_locations":["Washington, DC"],"file_type":"485BXT","file_description":"POST EFFECTIVE AMENDMENT","inc_states":["DE"],"items":[]}},{"_index":"edgar_file","_id":"0001999371-25-014003:saudi-485bxt_092525.htm","_score":25.294567,"_source":{"ciks":["0001944285"],"period_ending":null,"file_num":["811-23823"],"display_names":["Tema ETF Trust  (CIK 0001944285)"],"xsl":null,"sequence":1,"root_forms":["485BXT"],"file_date":"2025-09-25","biz_states":["DC"],"sics":[],"form":"485BXT","adsh":"0001999371-25-014003","film_num":["251343788"],"biz_locations":["Washington, DC"],"file_type":"485BXT","file_description":"POST EFFECTIVE AMENDMENT","inc_states":["DE"],"items":[]}},{"_index":"edgar_file","_id":"0001839882-23-010118:ex99-p1.htm","_score":25.290138,"_source":{"ciks":["0001944285"],"period_ending":null,"file_num":["811-23823"],"display_names":["Tema ETF Trust  (CIK 0001944285)"],"xsl":null,"sequence":12,"root_forms":["N-1A"],"file_date":"2023-04-21","biz_states":["DC"],"sics":[],"form":"N-1A/A","adsh":"0001839882-23-010118","film_num":["23836871"],"biz_locations":["Washington, DC"],"file_type":"EX-99.(P)(1)","file_description":"CODE OF ETHICS","inc_states":["DE"],"items":[]}},{"_index":"edgar_file","_id":"0001999371-25-008348:ex99-d4.htm","_score":25.287447,"_source":{"ciks":["0001944285"],"period_ending":null,"file_num":["811-23823"],"display_names":["Tema ETF Trust  (CIK 0001944285)"],"xsl":null,"sequence":"3","root_forms":["485BPOS"],"file_date":"2025-06-26","biz_states":["DC"],"sics":[],"form":"485BPOS","adsh":"0001999371-25-008348","film_num":["251078574"],"biz_locations":["Washington, DC"],"file_type":"EX-99.(D)(4)","file_description":"INVESTMENT SUB-ADVISORY AGREEMENT","inc_states":["DE"],"items":[]}},{"_index":"edgar_file","_id":"0001387131-23-009617:roya-8a12b_081023.htm","_score":25.275066,"_source":{"ciks":["0001944285"],"period_ending":null,"file_num":["001-41700"],"display_names":["Tema ETF Trust  (CIK 0001944285)"],"xsl":null,"sequence":1,"root_forms":["8-A12B"],"file_date":"2023-08-10","biz_states":["DC"],"sics":[],"form":"8-A12B","adsh":"0001387131-23-009617","film_num":["231160195"],"biz_locations":["Washington, DC"],"file_type":"8-A12B","file_description":"FORM 8-A12B","inc_states":["DE"],"items":[]}},{"_index":"edgar_file","_id":"0001999371-25-020654:family-485bxt_121825.htm","_score":25.270863,"_source":{"ciks":["0001944285"],"period_ending":null,"file_num":["811-23823"],"display_names":["Tema ETF Trust  (CIK 0001944285)"],"xsl":null,"sequence":1,"root_forms":["485BXT"],"file_date":"2025-12-18","biz_states":["DC"],"sics":[],"form":"485BXT","adsh":"0001999371-25-020654","film_num":["251582921"],"biz_locations":["Washington, DC"],"file_type":"485BXT","file_description":"POST-EFFECTIVE AMENDMENT","inc_states":["DE"],"items":[]}},{"_index":"edgar_file","_id":"0001839882-24-043900:saudiarabia-485bxt_120524.htm","_score":25.26702,"_source":{"ciks":["0001944285"],"period_ending":null,"file_num":["811-23823"],"display_names":["Tema ETF Trust  (CIK 0001944285)"],"xsl":null,"sequence":1,"root_forms":["485BXT"],"file_date":"2024-12-05","biz_states":["DC"],"sics":[],"form":"485BXT","adsh":"0001839882-24-043900","film_num":["241529737"],"biz_locations":["Washington, DC"],"file_type":"485BXT","file_description":"POST-EFFECTIVE AMENDMENT","inc_states":["DE"],"items":[]}},{"_index":"edgar_file","_id":"0001999371-25-007617:familyoffice-485bxt_061125.htm","_score":25.235569,"_source":{"ciks":["0001944285"],"period_ending":null,"file_num":["811-23823"],"display_names":["Tema ETF Trust  (CIK 0001944285)"],"xsl":null,"sequence":1,"root_forms":["485BXT"],"file_date":"2025-06-11","biz_states":["DC"],"sics":[],"form":"485BXT","adsh":"0001999371-25-007617","film_num":["251040041"],"biz_locations":["Washington, DC"],"file_type":"485BXT","file_description":"POST EFFECTIVE AMENDMENT","inc_states":["DE"],"items":[]}},{"_index":"edgar_file","_id":"0001839882-24-041549:tema-485bxt_112624.htm","_score":25.232765,"_source":{"ciks":["0001944285"],"period_ending":null,"file_num":["811-23823"],"display_names":["Tema ETF Trust  (CIK 0001944285)"],"xsl":null,"sequence":1,"root_forms":["485BXT"],"file_date":"2024-11-26","biz_states":["DC"],"sics":[],"form":"485BXT","adsh":"0001839882-24-041549","film_num":["241505174"],"biz_locations":["Washington, DC"],"file_type":"485BXT","file_description":"POST EFFECTIVE AMENDMENT","inc_states":["DE"],"items":[]}},{"_index":"edgar_file","_id":"0001999371-26-000970:family-485bxt_011526.htm","_score":25.22793,"_source":{"ciks":["0001944285"],"period_ending":null,"file_num":["811-23823"],"display_names":["Tema ETF Trust  (CIK 0001944285)"],"xsl":null,"sequence":1,"root_forms":["485BXT"],"file_date":"2026-01-15","biz_states":["DC"],"sics":[],"form":"485BXT","adsh":"0001999371-26-000970","film_num":["26535639"],"biz_locations":["Washington, DC"],"file_type":"485BXT","file_description":"POST-EFFECTIVE AMENDMENT","inc_states":["DE"],"items":[]}},{"_index":"edgar_file","_id":"0001839882-24-046220:saudiarabia-485bxt_121924.htm","_score":25.2188,"_source":{"ciks":["0001944285"],"period_ending":null,"file_num":["811-23823"],"display_names":["Tema ETF Trust  (CIK 0001944285)"],"xsl":null,"sequence":1,"root_forms":["485BXT"],"file_date":"2024-12-19","biz_states":["DC"],"sics":[],"form":"485BXT","adsh":"0001839882-24-046220","film_num":["241563958"],"biz_locations":["Washington, DC"],"file_type":"485BXT","file_description":"POST EFFECTIVE AMENDMENT","inc_states":["DE"],"items":[]}},{"_index":"edgar_file","_id":"0001999371-25-003099:dspy_485bpos-032525.htm","_score":25.197968,"_source":{"ciks":["0001944285"],"period_ending":null,"file_num":["811-23823"],"display_names":["Tema ETF Trust  (CIK 0001944285)"],"xsl":null,"sequence":1,"root_forms":["485BPOS"],"file_date":"2025-03-25","biz_states":["DC"],"sics":[],"form":"485BPOS","adsh":"0001999371-25-003099","film_num":["25767901"],"biz_locations":["Washington, DC"],"file_type":"485BPOS","file_description":"POST-EFFECTIVE AMENDMENT TO RULE 485(B)","inc_states":["DE"],"items":[]}},{"_index":"edgar_file","_id":"0001145549-24-002280:royavconfidential.htm","_score":25.168991,"_source":{"ciks":["0001944285"],"period_ending":"2023-11-30","file_num":["811-23823"],"display_names":["Tema ETF Trust  (CIK 0001944285)"],"xsl":null,"sequence":2,"root_forms":["NPORT-P"],"file_date":"2024-01-23","biz_states":["DC"],"sics":[],"form":"NPORT-P","adsh":"0001145549-24-002280","film_num":["24551248"],"biz_locations":["Washington, DC"],"file_type":"NPORT-EX","file_description":"PART F","inc_states":["DE"],"items":[]}},{"_index":"edgar_file","_id":"0001839882-24-046216:tema-485bxt_121924.htm","_score":25.161983,"_source":{"ciks":["0001944285"],"period_ending":null,"file_num":["811-23823"],"display_names":["Tema ETF Trust  (CIK 0001944285)"],"xsl":null,"sequence":1,"root_forms":["485BXT"],"file_date":"2024-12-19","biz_states":["DC"],"sics":[],"form":"485BXT","adsh":"0001839882-24-046216","film_num":["241563744"],"biz_locations":["Washington, DC"],"file_type":"485BXT","file_description":"POST EFFECTIVE AMENDMENT","inc_states":["DE"],"items":[]}},{"_index":"edgar_file","_id":"0001999371-25-012950:tema-8a12b_090925.htm","_score":25.161194,"_source":{"ciks":["0001944285"],"period_ending":null,"file_num":["001-41700"],"display_names":["Tema ETF Trust  (CIK 0001944285)"],"xsl":null,"sequence":1,"root_forms":["8-A12B"],"file_date":"2025-09-09","biz_states":["DC"],"sics":[],"form":"8-A12B","adsh":"0001999371-25-012950","film_num":["251303883"],"biz_locations":["Washington, DC"],"file_type":"8-A12B","file_description":"FORM FOR THE REGISTRATION","inc_states":["DE"],"items":[]}},{"_index":"edgar_file","_id":"0001999371-25-013946:tema-8a12b_092425.htm","_score":25.15423,"_source":{"ciks":["0001944285"],"period_ending":null,"file_num":["001-41700"],"display_names":["Tema ETF Trust  (CIK 0001944285)"],"xsl":null,"sequence":1,"root_forms":["8-A12B"],"file_date":"2025-09-24","biz_states":["DC"],"sics":[],"form":"8-A12B","adsh":"0001999371-25-013946","film_num":["251338319"],"biz_locations":["Washington, DC"],"file_type":"8-A12B","file_description":"FORM FOR THE REGISTRATION","inc_states":["DE"],"items":[]}}]},"aggregations":{"entity_filter":{"doc_count_error_upper_bound":0,"sum_other_doc_count":770,"buckets":[{"key":"Tema ETF Trust  (CIK 0001944285)","doc_count":418},{"key":"Tidal Trust II  (CIK 0001924868)","doc_count":191},{"key":"ETF Opportunities Trust  (CIK 0001771146)","doc_count":187},{"key":"Listed Funds Trust  (CIK 0001683471)","doc_count":103},{"key":"Tidal Trust III  (CIK 0001722388)","doc_count":70},{"key":"Innovator ETFs Trust  (CIK 0001415726)","doc_count":68},{"key":"NEOS ETF Trust  (CIK 0001848758)","doc_count":67},{"key":"WisdomTree Trust  (CIK 0001350487)","doc_count":67},{"key":"World Funds Trust  (CIK 0001396092)","doc_count":46},{"key":"Exchange Listed Funds Trust  (CIK 0001547950)","doc_count":43},{"key":"Simplify Exchange Traded Funds  (CIK 0001810747)","doc_count":43},{"key":"AIM ETF Products Trust  (CIK 0001797318)","doc_count":36},{"key":"Tidal Trust I  (CIK 0001742912)","doc_count":30},{"key":"Harbor ETF Trust  (CIK 0001860434)","doc_count":27},{"key":"Morgan Stanley ETF Trust  (CIK 0001676326)","doc_count":26},{"key":"AB Active ETFs, Inc.  (CIK 0001496608)","doc_count":25},{"key":"FORUM FUNDS  (CIK 0000315774)","doc_count":24},{"key":"Grayscale Funds Trust  (CIK 0001976672)","doc_count":24},{"key":"RBB Fund Trust  (CIK 0001618627)","doc_count":23},{"key":"TRUST FOR PROFESSIONAL MANAGERS  (CIK 0001141819)","doc_count":23},{"key":"ETF Series Solutions  (CIK 0001540305)","doc_count":22},{"key":"REX ETF Trust  (CIK 0002043954)","doc_count":22},{"key":"Tidal ETF Trust  (CIK 0001742912)","doc_count":22},{"key":"2023 ETF Series Trust  (CIK 0001969674)","doc_count":21},{"key":"CHARLES SCHWAB FAMILY OF FUNDS  (CIK 0000857156)","doc_count":20},{"key":"John Hancock Exchange-Traded Fund Trust  (CIK 0001478482)","doc_count":20},{"key":"Kurv ETF Trust  (CIK 0001782952)","doc_count":20},{"key":"Strategy Shares  (CIK 0001506213)","doc_count":20},{"key":"AMERICAN CENTURY ETF TRUST  (CIK 0001710607)","doc_count":17},{"key":"Exchange Place Advisors Trust  (CIK 0001750821)","doc_count":14}]},"sic_filter":{"doc_count_error_upper_bound":0,"sum_other_doc_count":0,"buckets":[{"key":"6021","doc_count":37},{"key":"6211","doc_count":18},{"key":"6029","doc_count":10},{"key":"4813","doc_count":8},{"key":"2621","doc_count":4},{"key":"4941","doc_count":4},{"key":"1040","doc_count":3},{"key":"2011","doc_count":2},{"key":"4911","doc_count":2},{"key":"3578","doc_count":1},{"key":"6022","doc_count":1}]},"biz_states_filter":{"doc_count_error_upper_bound":0,"sum_other_doc_count":50,"buckets":[{"key":"WI","doc_count":464},{"key":"DC","doc_count":418},{"key":"NY","doc_count":307},{"key":"VA","doc_count":234},{"key":"IL","doc_count":171},{"key":"CT","doc_count":126},{"key":"DE","doc_count":93},{"key":"CA","doc_count":71},{"key":"MA","doc_count":59},{"key":"ME","doc_count":56},{"key":"MN","doc_count":51},{"key":"OH","doc_count":47},{"key":"FL","doc_count":46},{"key":"OK","doc_count":43},{"key":"PA","doc_count":34},{"key":"MO","doc_count":30},{"key":"MI","doc_count":23},{"key":"D5","doc_count":18},{"key":"TN","doc_count":18},{"key":"CO","doc_count":17},{"key":"NC","doc_count":17},{"key":"AZ","doc_count":16},{"key":"GA","doc_count":16},{"key":"MD","doc_count":13},{"key":"NJ","doc_count":12},{"key":"NV","doc_count":12},{"key":"AL","doc_count":10},{"key":"TX","doc_count":10},{"key":"V8","doc_count":10},{"key":"IA","doc_count":9}]},"form_filter":{"doc_count_error_upper_bound":0,"sum_other_doc_count":5,"buckets":[{"key":"485BPOS","doc_count":969},{"key":"485APOS","doc_count":597},{"key":"13F-HR","doc_count":397},{"key":"485BXT","doc_count":111},{"key":"NPORT-P","doc_count":109},{"key":"497","doc_count":57},{"key":"497K","doc_count":46},{"key":"N-1A","doc_count":43},{"key":"N-MFP3","doc_count":26},{"key":"6-K","doc_count":19},{"key":"POS EX","doc_count":15},{"key":"8-A12B","doc_count":12},{"key":"CERT","doc_count":12},{"key":"N-CSR","doc_count":12},{"key":"40-APP","doc_count":9},{"key":"N-CSRS","doc_count":9},{"key":"N-14","doc_count":8},{"key":"497J","doc_count":7},{"key":"N-CEN","doc_count":6},{"key":"N-2","doc_count":4},{"key":"20-F","doc_count":3},{"key":"25-NSE","doc_count":3},{"key":"40-17G","doc_count":3},{"key":"N-PX","doc_count":3},{"key":"24F-2NT","doc_count":2},{"key":"N-MFP2","doc_count":2},{"key":"SCHEDULE 13G","doc_count":2},{"key":"8-K","doc_count":1},{"key":"AW","doc_count":1},{"key":"CB","doc_count":1}]}},"query":{"_source":{"exclude":["doc_text"]},"query":{"bool":{"must":[{"match_phrase":{"doc_text":"Tema"}},{"match_phrase":{"doc_text":"ETF"}}],"must_not":[],"should":[],"filter":[{"range":{"file_date":{"gte":"2023-01-01","lte":"2026-03-03"}}}]}},"from":0,"size":100,"aggregations":{"form_filter":{"terms":{"field":"root_forms","size":30}},"entity_filter":{"terms":{"field":"display_names.raw","size":30}},"sic_filter":{"terms":{"field":"sics","size":30}},"biz_states_filter":{"terms":{"field":"biz_states","size":30}}}}}